{"Task": {"name": "RandomTargetReachWithLoads", "delay_range": [0, 0], "do_recompute_targets": false, "dt": 0.01, "endpoint_load": 3.0, "initial_joint_state": null, "initial_joint_state_original": null, "n_initial_joint_states": null, "training_batch_size": 32, "training_n_timesteps": 100, "losses": [{"assigned output": "cartesian position", "loss object": "<motornet.nets.losses.PositionLoss object at 0x000002D36EB3CA90>", "loss name": "position", "loss weight": 1.0, "compounded": false}, {"assigned output": "muscle state", "loss object": "<motornet.nets.losses.L2xDxActivationLoss object at 0x000002D36EB3CA00>", "loss name": "l2_xdx_activation", "loss weight": 5, "compounded": false}, {"assigned output": "gru_hidden_0", "loss object": "<motornet.nets.losses.L2xDxRegularizer object at 0x000002D36EB3C9A0>", "loss name": "gru_regularizer", "loss weight": 0.1, "compounded": false}]}, "Network": {"hidden_noise_sd": 0.0, "kernel_regularizer_weight": 1e-06, "recurrent_regularizer_weight": 0.0, "n_units": 50, "n_hidden_layers": 1, "activation": "tanh", "proprioceptive_noise_sd": 0.0, "visual_noise_sd": 0.0, "proprioceptive_delay": 1, "visual_delay": 1, "n_muscle": 4, "n_ministeps": 1}, "Plant": {"Muscle": {"name": "ReluMuscle", "state names": ["excitation/activation", "muscle length", "muscle velocity", "force"]}, "Skeleton": {"dof": 2, "dt": "0.01", "space_dim": 2, "mass": 1}, "dt": 0.01, "muscle_names": ["UpperRight", "UpperLeft", "LowerRight", "LowerLeft"], "excitation_noise_sd": 0.0, "n_muscles": 4, "proprioceptive_delay": 1, "visual_delay": 1, "muscle_wrapping_cfg": {"UpperRight": {"n_fixation_points": 2, "fixation body": [0, 1], "coordinates": [[2.0, 2.0], [0.0, 0.0]], "max_isometric_force": 500}, "UpperLeft": {"n_fixation_points": 2, "fixation body": [0, 1], "coordinates": [[-2.0, 2.0], [0.0, 0.0]], "max_isometric_force": 500}, "LowerRight": {"n_fixation_points": 2, "fixation body": [0, 1], "coordinates": [[2.0, -2.0], [0.0, 0.0]], "max_isometric_force": 500}, "LowerLeft": {"n_fixation_points": 2, "fixation body": [0, 1], "coordinates": [[-2.0, -2.0], [0.0, 0.0]], "max_isometric_force": 500}}}}